{
    "_id": "course",
    "_type": "course",
    "title": "Open Data in Practice",
    "displayTitle": "Open Data in Practice",
    "format": "course",
    "_buttons": {
        "submit": "Submit",
        "reset": "Reset",
        "showCorrectAnswer": "Model Answer",
        "hideCorrectAnswer": "My Answer"
    },
    "_latestTrackingId": 13,
    "_learningOutcomes": [
    {
        "outcome": "Describe the open data publication phases",
        "credits": 5,
        "badge": "strategist"
    },
    {
        "outcome": "Identify a number of key processes to improve the sustainable publication of open data",
        "credits": 5,
        "badge": "strategist"
    },
    {
        "outcome": "Apply a number of open data guidelines to ensure open data becomes sustainable",
        "credits": 10,
        "badge": "strategist"
    },
    {
        "outcome": "Identify different characteristics in data and associated data formats",
        "credits": 5,
        "badge": "practitioner"
    },
    {
        "outcome": "Justify approaches for publishing different types of data in different ways",
        "credits": 10,
        "badge": "practitioner"
    },
    {
        "outcome": "Describe the data spectrum and how it applies to different types of data ",
        "credits": 10,
        "badge": "strategist"
    },
    {
        "outcome": "Describe the importance of persistent identifiers for data",
        "credits": 5,
        "badge": "strategist"
    },
    {
        "outcome": "Apply the five stars of linked open data to analyse technical quality of data",
        "credits": 10,
        "badge": "practitioner"
    },
    {
        "outcome": "Explain the difference between the data on the web and the “web of data”",
        "credits": 5,
        "badge": "strategist"
    },
    {
        "outcome": "List a number of patterns for discovering open data on and in the web",
        "credits": 5,
        "badge": "practitioner"
    },
    {
        "outcome": "Create search patterns that enable discovery of open data",
        "credits": 10,
        "badge": "practitioner"
    },
    {
        "outcome": "Analyse the challenges in using existing open data",
        "credits": 10,
        "badge": "strategist"
    },
    {
        "outcome": "Analyse the benefits and drawbacks of publishing data on different open data platforms",
        "credits": 10,
        "badge": "strategist"
    },
    {
        "outcome": "Describe the approaches for publishing data",
        "credits": 5,
        "badge": "strategist"
    },
    {
        "outcome": "Differentiate between data catalogues, data portals and data management systems”",
        "credits": 5,
        "badge": "strategist"
    },
    {
        "outcome": "Publish a number of datasets on different open data platforms",
        "credits": 15,
        "badge": "practitioner"
    },
    {
        "outcome": "Create a process model for publishing different data sets",
        "credits": 10,
        "badge": "practitioner"
    }
    ],
    "_resources": [
    {},
    {
        "title": "Slides and Exercises",
        "description": "Access key course materials",
        "_filterButtons": {
            "all": "All",
            "document": "PDF",
            "media": "Media",
            "link": "Link"
        },
        "_resourcesItems": [
    	    {
       	 	"_type": "link",
        	"title": "Best Practices",
        	"description": "Slides for the second afternoon session",
        	"_link": "http://theodi.github.io/presentations/training-law-best-practice.html#/13"
    	   }
    	]
     },
     {
        "title": "Links and resources",
        "description": "Examples and links for course",
        "_filterButtons": {
            "all": "All",
            "document": "PDF",
            "media": "Media",
            "link": "Link"
        },
        "_resourcesItems": [
          {
        	"_type": "link",
        	"title": "Open Refine",
        	"description": "The Open Refine tool is a powerful tool for cleaning messy data",
        	"_link": "http://openrefine.org/download.html"
    	  },
    	  {
        	"_type": "link",
        	"title": "CSV Lint",
        	"description": "CSVLint helps you to check that your CSV open data file is readable",
        	"_link": "http://csvlint.io/"
    	  },
    	  {
        	"_type": "link",
        	"title": "CSV Dataset Health Checker",
        	"description": "The CSV dataset health checker is a simple way to check how many variations a CSV open dataset has gone through and whether all of the files are the same or different",
        	"_link": "http://theodi.github.io/csv-dataset-validator/"
    	  },
    	  {
        	"_type": "link",
        	"title": "JSON Lint",
        	"description": "JSONLint helps you to check that your JSON open data file is readable",
        	"_link": "http://jsonlint.com/"
    	  },
        {
        "_type": "link",
        "title": "Publisher's Guide to Open Data Licensing",
        "description": "How to licence your open data",
        "_link": "http://theodi.org/guides/publishers-guide-open-data-licensing"
    },
    {
        "_type": "link",
        "title": "Reuser's Guide to Open Data Licensing",
        "description": "How to understand the licence on your open data",
        "_link": "http://theodi.org/guides/reusers-guide-open-data-licensing"
    },
    {
        "_type": "link",
        "title": "Publisher's Guide to the Open Data Rights Management",
        "description": "How to manage the rights of your open data",
        "_link": "http://theodi.org/guides/publishers-guide-to-the-open-data-rights-statement-vocabulary"
    },
    {
        "_type": "link",
        "title": "Reuser's Guide to the Open Data Rights Management",
        "description": "How to understand your rights in using open data",
        "_link": "http://theodi.org/guides/odrs-reusers-guide"
    }
    ]
    },
    {
        "title": "Credits and attribution",
        "description": "View attribution for licensed content",
        "_filterButtons": {
            "all": "All",
            "document": "PDF",
            "media": "Media",
            "link": "Link"
        },
        "_resourcesItems": [
    	]
    }
]
}
